codecraft/__init__.py
codecraft/core/__init__.py
codecraft/core/builder.py
codecraft/core/context.py
codecraft/core/node.py
codecraft/elements/__init__.py
codecraft/elements/class_element.py
codecraft/elements/control_flow.py
codecraft/elements/decorators.py
codecraft/elements/function_element.py
codecraft/elements/imports.py
codecraft/utils/__init__.py
codecraft/utils/helpers.py
codecraft/utils/indentation.py
pycodecraft-0.1.0.dist-info/METADATA
pycodecraft-0.1.0.dist-info/WHEEL
pycodecraft-0.1.0.dist-info/entry_points.txt
pycodecraft-0.1.0.dist-info/RECORD
