Metadata-Version: 2.1
Name: pycodecraft
Version: 0.1.0
Summary: A Pythonic library for programmatic code generation using elegant context managers
Keywords: code-generation,codegen,ast,python,metaprogramming
Author-Email: Victor Gabriel Deon <victorgabrieldeon@gmail.com>
License: MIT
Classifier: Development Status :: 4 - Beta
Classifier: Intended Audience :: Developers
Classifier: License :: OSI Approved :: MIT License
Classifier: Programming Language :: Python :: 3
Classifier: Programming Language :: Python :: 3.8
Classifier: Programming Language :: Python :: 3.9
Classifier: Programming Language :: Python :: 3.10
Classifier: Programming Language :: Python :: 3.11
Classifier: Programming Language :: Python :: 3.12
Classifier: Topic :: Software Development :: Code Generators
Classifier: Topic :: Software Development :: Libraries :: Python Modules
Classifier: Typing :: Typed
Project-URL: Homepage, https://github.com/victorgabrieldeon/code-craft
Project-URL: Repository, https://github.com/victorgabrieldeon/code-craft
Project-URL: Documentation, https://github.com/victorgabrieldeon/code-craft#readme
Project-URL: Bug Tracker, https://github.com/victorgabrieldeon/code-craft/issues
Requires-Python: >=3.8
Requires-Dist: typing-extensions>=4.0.0
Provides-Extra: dev
Requires-Dist: pytest>=7.0.0; extra == "dev"
Requires-Dist: pytest-cov>=4.0.0; extra == "dev"
Requires-Dist: mypy>=1.0.0; extra == "dev"
Requires-Dist: ruff>=0.1.0; extra == "dev"
Requires-Dist: black>=23.0.0; extra == "dev"
Provides-Extra: format
Requires-Dist: black>=23.0.0; extra == "format"
